{"Disposition":"Unknown","map":"<A HREF = \"http://maps.google.com/maps?q=40.427295,+-78.388902(11925)&iwloc=A&hl=en\"> mufon case (11925) map </A>","Country":"United States","Date Submitted":"07/29/2008 12:00 UTC","trends":["There have been 5 other sightings in Hollidaysburg","There were no other sightings in Hollidaysburg on or around July 29th 2008","This sighting has never been favorited.",""],"Weather Factors":"Unknown","divs":["sighting detailsa weird glowing object flew over during the day, witnessed by myself and 2 sons. i got video and 2 photos of it. could be the space station, but it was damn low if it was. check out the video and pics. their was no noise heard coming from it. it was flying south west. from hollidaysburg\\duncansville, pa toward blue knob."],"files":["/var/www/straped/mufon/html2text/11925.html.txt","/var/www/straped/mufon/more/11925_submitter_file1__039.JPG","/var/www/straped/mufon/more/11925_submitter_file2__040.JPG","/var/www/straped/mufon/org/11925.html"],"Log Number":"US-08042008-0025","Object Features":"Undisclosed","Object Flight Path":"Undisclosed","Source":"MUFON","Summary":"wierd glowing object flying over during the day","Viewing Distance":"Unknown","Date of the Event":"07/29/2008 12:00 UTC","Latitude":"40.427295","City":"Hollidaysburg","Object Shape":"Cylinder","Tags":"City","Case Number":"11925","Region":"Pennsylvania","Longitude":"-78.388902","Sighting Duration":"Undisclosed"}