{"Latitude":"33.753975","files":["/var/www/straped/mufon/html2text/14316.html.txt","/var/www/straped/mufon/org/14316.html"],"Object Features":"Dome","Weather Factors":"None","Sighting Duration":"01:01:00","Object Shape":"Cylinder, Disc, Flash","Case Number":"14316","Disposition":"Hoax","Log Number":"US-12092008-0004","Source":"MUFON","Date Submitted":"12/08/2008 10:45 UTC","Tags":"City","map":"<A HREF = \"http://maps.google.com/maps?q=33.753975,+-84.386262(14316)&iwloc=A&hl=en\"> mufon case (14316) map </A>","Summary":"looked out window at atars,i noticed a large orange object, then it flashed and was done. iI saw several more small objects. they were so active.","trends":["There have been 95 other sightings in Atlanta","There were no other sightings in Atlanta on or around December 8th 2008"],"Longitude":"-84.386262","City":"Atlanta","Country":"United States","Object Flight Path":"Stationary,Hovering then path,Path then hovering","Viewing Distance":"101-500 Feet","Date of the Event":"12/08/2008 10:45 UTC","Region":"Georgia","divs":["Sighting Detailslooked out of window at planets, I then notice a large orange,glowing object roof top, It then looked like an explosion into silver, it dissappeared. there were several small objects moving for at least l-hr.I was dizzy, and sick for about several hours after this event. I did not sleep at all. I felt threatened."]}