{"Summary":"UFO in Obama inauguration video.","Date of the Event":"01/20/2009 01:00 UTC","Viewing Distance":"Unknown","Source":"MUFON","Tags":"City","City":"Washington","trends":["There have been 54 other sightings in Washington","There were 3 other sightings in Washington on or around January 20th 2009"],"Log Number":"US-01222009-0002","files":["/var/www/straped/mufon/html2text/15043.html.txt","/var/www/straped/mufon/org/15043.html"],"Sighting Duration":"Undisclosed","divs":["sighting detailsi saw the prior report regarding the same event on this the tracker. i decided to do a little research on cnn's sight and found the video the prior person was referencing. i don't know what it is. it could be a bird, or it could be a high speed craft of some sort. i think it does merit further analysis. the link can be found below. sorry you'll have to sit through a commercial. the object enters from the right about 8 seconds into the video and travels across the entire screen. i would love to know if this is authentic or if it is a bird. http:\\\\www.cnn.com\\video\\#\\video\\politics\\2009\\01\\20\\inaug.blitz.gergen.obrien.cnn?iref=videosearch"],"Longitude":"-77.027926","Weather Factors":"Unknown","Region":"District of Columbia","Case Number":"15043","Latitude":"38.900882","Object Shape":"Cigar","Object Flight Path":"Undisclosed","Object Features":"Undisclosed","Country":"United States","Date Submitted":"01/20/2009 01:00 UTC","map":"<A HREF = \"http://maps.google.com/maps?q=38.900882,+-77.027926(15043)&iwloc=A&hl=en\"> mufon case (15043) map </A>","Disposition":"Unresolved"}