{"Date Submitted":"01/27/2010 11:36 UTC","Source":"MUFON","Date of the Event":"01/27/2010 09:45 UTC","Region":"Florida","Object Shape":"Bullet, Missile, Fireball","Tags":"City","Case Number":"21688","Summary":"watch a fireball move south to north with a wobbley flight ...thought they had launch the shuttle","Longitude":"-82.63296","trends":["There have been 4 other sightings in Lake City","There were no other sightings in Lake City on or around January 27th 2010"],"Object Features":"Undisclosed","Log Number":"US-01272010-0014","Sighting Duration":"Undisclosed","Disposition":"Unknown","divs":["Sighting Detailswas standing in my friends front yard , look to the south , seen a yellow star didnt pay it know mind until my friend came outside and seen it , it was moving north fast , we got the rifle out of the truck it has a high power scope , look at it , it had no strobes no light at all , it had a fireball on it ass , wobbled as it flew by ,we watched it heading north until we could no longer see it, i thought i herd a rocket thats why i thought nasa had launch the shuttle but they didnt . to me it kinda look like a ICBM flying except for the wobbley flight.this make my third sighting."],"map":"<A HREF = \"http://maps.google.com/maps?q=30.192206,+-82.63296(21688)&iwloc=A&hl=en\"> mufon case (21688) map </A>","Viewing Distance":"Unknown","Weather Factors":"Unknown","files":["/var/www/straped/mufon/html2text/21688.html.txt","/var/www/straped/mufon/org/21688.html"],"Latitude":"30.192206","Country":"United States","City":"Lake City","Object Flight Path":"Undisclosed"}