{"trends":["There have been 14 other sightings in Fairfax","There were no other sightings in Fairfax on or around May 29th 2011","This sighting has never been favorited.",""],"Tags":"City","Object Features":"Undisclosed","Object Shape":"Oval","Date of the Event":"05/29/2011 06:30 UTC","Latitude":"38.851374","City":"Fairfax","Country":"United States","Weather Factors":"Unknown","Summary":"Unknown Object Over Fairfax, Virginia - May 29, 2011","Sighting Duration":"Undisclosed","Object Flight Path":"Undisclosed","Region":"Virginia","Log Number":"US-06102011-0014","Longitude":"-77.299143","Disposition":"Insufficient Data","map":"<A HREF = \"http://maps.google.com/maps?q=38.851374,+-77.299143(29482)&iwloc=A&hl=en\"> mufon case (29482) map </A>","Date Submitted":"06/10/2011 09:15 UTC","Case Number":"29482","Source":"MUFON","divs":["sighting detailsthis object was filmed over fairfax, va from ~ 7 - 8:30 p.m. on sunday, may 29, 2011. it was visible from starting at approximately 6:30 p.m. and abruptly faded from sight at 8:43 exactly. it was seen for two evenings in a row. i constantly sky-gaze in this direction, watching flight and weather patterns, and i did not notice anything like this in the days or evenings beforehand. it was seen in the eastern \\ south eastern sky. it is not venus, as venus, though visible during daylight this month, appears early morning. it is also not the iss or endeavor, as they were docked together, and were only visible that day over asia. it is also not saturn. although saturn was visible during sunset this month, the light pollution and air pollution of this area at the time would have made it impossible to see at that time. it also appeared much earlier than saturn, and faded from view much earlier than saturn, which should have been visible until near sunset. the direction it was first spotted, which was north east, does not fit the orbital location of saturn at the time, which would put saturn in the south eastern sky. the object also had a slightly erratic flight path, unlike that of a planet or star. it is also oval shaped and bears a shadow on its bottom. if it was saturn, or any planet, it's shadow would not be located there, considering the sun was hanging low in the sky, although not yet at horizon level. my sources are stellarium, astronomy.com's stardome and google earth which i used for exact directions, altitudes, and orbital information. according to stellarium with an ocean landscape to simulate sea level (fairfax is 312 above sea level) and being set to perspective mode, arcturus would have only been directly north east at 4 p.m. not only would i not be able to see it with this much daylight, it would be below our roof, right under the horizon, effectively out of sight completely. even at 6 p.m. arcturus would be directly east. at 6 p.m. the object was north east. this video is not edited. i didn't know how to use the camera at first, so i didn't know i was recording in the beginning plus i felt that editing it would decrease credibility, so i left it unedited. and please excuse my language. my brother was being very annoying. what i find very strange is that usually when a planet or bright star is observable during the daytime, they are usually mistaken for a ufo, and the reports pour in on mufon and elsewhere. i have seen nothing on here or elsewhere similar to this on these dates, unless the 3rd party on the form is an audio \\ video expert, i do not consent to this being distributed. also, i accidentally forgot to fill in some details on the form, so i am very sorry if i have made a duplicate post on the site."],"files":["/var/www/straped/mufon/html2text/29482.html.txt","/var/www/straped/mufon/org/29482.html"],"Viewing Distance":"Unknown"}