{"Object Flight Path":"Unknown","files":["/var/www/straped/mufon/html2text/30301.html.txt","/var/www/straped/mufon/org/30301.html"],"Viewing Distance":"Unknown","trends":["There have been 112 other sightings in Orlando","There were no other sightings in Orlando on or around June 1st 2011","This sighting has never been favorited.",""],"Sighting Duration":"Undisclosed","Source":"MUFON","Tags":"City","Latitude":"28.543406","Date Submitted":"08/01/2011 03:14 UTC","map":"<A HREF = \"http://maps.google.com/maps?q=28.543406,+-81.375176(30301)&iwloc=A&hl=en\"> mufon case (30301) map </A>","Longitude":"-81.375176","Weather Factors":"None","divs":["Sighting DetailsDidn't see anything. Noise and house shook. Looked outside. Didn't see anything. Automatic lights were on by garage. Went back to bed. Today July 22, 2011. Walked back home across the commons and saw a visible circle in the grass outside my living room window. Wow! Pretty strange. No idea what it is or what caused it."],"Object Shape":"Unknown","Log Number":"US-08012011-0024","Disposition":"Unresolved","Date of the Event":"06/01/2011 12:00 UTC","Country":"United States","Object Features":"Unknown","City":"Orlando","Case Number":"30301","Region":"Florida","Summary":"Heard loud noise, got up looked out of window garage lights were on."}