{"Country":"Chile","Log Number":"CL-01252012-0019","Object Flight Path":"Stationary","Disposition":"Unresolved","Longitude":"-70.68106","Source":"MUFON","divs":["Sighting DetailsAlong with several friends sat on the sidewalk to rest after playing all afternoon and talk. We spent an hour talking about UFOs, and then another 30 minutes talking about the pyramids. Most of my friends was about 11 years, my older friends were between 15 to 16 years. When our mothers called us to go home, some look at the sky and some of my younger friends said it was small flying saucer, old friends said it was a plane or a helicopter, but then stopped the flying object noiselessly, and when all my friends saw the flying object that rose vertically until it was lost quickly in less than a second."],"Viewing Distance":"21-100 Feet","Summary":"anecdotal sightings","Sighting Duration":"00:05:00","Date Submitted":"01/25/2012 05:19 UTC","Region":"Santiago Metropolitan Region","City":"Santiago","map":"<A HREF = \"http://maps.google.com/maps?q=-33.501531,+-70.68106(35138)&iwloc=A&hl=en\"> mufon case (35138) map </A>","Date of the Event":"01/10/1994 12:00 UTC","Case Number":"35138","Object Features":"Unknown","Tags":"City","Latitude":"-33.501531","trends":["There have been 12 other sightings in Santiago","There were no other sightings in Santiago on or around January 10th 1994"],"files":["/var/www/straped/mufon/html2text/35138.html.txt","/var/www/straped/mufon/org/35138.html"],"Weather Factors":"Unknown","Object Shape":"Circle, Disc"}