{"Country":"United States","Disposition":"Unresolved","Summary":"while returning from las vegas with 2 friends in car i was driving south onhwy 15 right behind the small airport close to the womens prison the disk came over the top of the mountain it came right at us and toward the freeway i looked at my friend and ask","Date of the Event":"03/20/1994 11:02 UTC","Object Flight Path":"Path then hovering","Region":"Nevada","Tags":"City","trends":["There have been no other sightings in jean nevada","This sighting has never been favorited."],"Case Number":"50029","Source":"MUFON","City":"jean nevada","Longitude":"-116.418389","Object Features":"Dome","Log Number":"US-08202013-0013","files":["/var/www/straped/mufon/html2text/50029.html.txt","/var/www/straped/mufon/org/50029.html"],"Viewing Distance":"101-500 Feet","Date Submitted":"08/20/2013 07:52 UTC","Weather Factors":"Unknown","map":"<A HREF = \"http://maps.google.com/maps?q=38.80449,+-116.418389(50029)&iwloc=A&hl=en\"> mufon case (50029) map </A>","Sighting Duration":"00:02:15","Object Shape":"Disc","divs":["Sighting Detailsill state thast while coming home from las vegas a metalic disk lifted off a near by moutain and approached us came about half way from the mountain top and did a wing tip rool then went back from exactly where it had taken off from this lasted about 2 minutes total i had a witness my passenger po box 553 oceanside ca i have many other encouters"],"Latitude":"38.80449"}