{"Longitude":"-82.242171","Sighting Duration":"Undisclosed","Disposition":"Unresolved","trends":["There has been one other sighting in Lithia","There were no other sightings in Lithia on or around October 20th 2013"],"files":["/var/www/straped/mufon/html2text/51687.html.txt","/var/www/straped/mufon/org/51687.html"],"Viewing Distance":"501 Feet - 1 Mile","Date of the Event":"10/20/2013 08:16 UTC","Tags":"City","Latitude":"27.838839","City":"Lithia","Object Flight Path":"Straight-line path","Object Shape":"Boomerang, Chevron","Summary":"Saw a boomerang shaped vehicle with numerous grey lights all the same color flying under the cloudcover","Object Features":"Unknown","Log Number":"US-10202013-0023","Date Submitted":"10/20/2013 08:51 UTC","Region":"Florida","Country":"United States","map":"<A HREF = \"http://maps.google.com/maps?q=27.838839,+-82.242171(51687)&iwloc=A&hl=en\"> mufon case (51687) map </A>","divs":["Sighting DetailsI was laying in my hot tub in the back yard looking straight up...from the west came an object with I would guess 9 lights all the same dull grey color. It was not traveling fast just steady. It was under the cloud cover and about 2 minutes later an airplane or chopper flew in the same general direction."],"Weather Factors":"Unknown","Case Number":"51687","Source":"MUFON"}